model/__init__.py
paddlevideo/__init__.py
paddlevideo/version.py
paddlevideo/loader/__init__.py
paddlevideo/loader/builder.py
paddlevideo/loader/registry.py
paddlevideo/loader/pipelines/__init__.py
paddlevideo/loader/pipelines/compose.py
paddlevideo/loader/pipelines/manet_pipeline.py
paddlevideo/modeling/__init__.py
paddlevideo/modeling/builder.py
paddlevideo/modeling/registry.py
paddlevideo/modeling/weight_init.py
paddlevideo/modeling/backbones/__init__.py
paddlevideo/modeling/backbones/aspp_manet.py
paddlevideo/modeling/backbones/decoder_manet.py
paddlevideo/modeling/backbones/deeplab_manet.py
paddlevideo/modeling/backbones/resnet_manet.py
paddlevideo/modeling/framework/__init__.py
paddlevideo/modeling/framework/segment/__init__.py
paddlevideo/modeling/framework/segment/base.py
paddlevideo/modeling/framework/segment/manet_stage1.py
paddlevideo/modeling/heads/IntVOS.py
paddlevideo/modeling/heads/__init__.py
paddlevideo/utils/__init__.py
paddlevideo/utils/build_utils.py
paddlevideo/utils/config.py
paddlevideo/utils/dist_utils.py
paddlevideo/utils/logger.py
paddlevideo/utils/manet_utils.py
paddlevideo/utils/precise_bn.py
paddlevideo/utils/profiler.py
paddlevideo/utils/record.py
paddlevideo/utils/registry.py
paddlevideo/utils/save_load.py
EIVideo-0.1a3.dev1.dist-info/METADATA
EIVideo-0.1a3.dev1.dist-info/WHEEL
EIVideo-0.1a3.dev1.dist-info/top_level.txt
EIVideo-0.1a3.dev1.dist-info/RECORD
