Metadata-Version: 2.1
Name: EIVideo
Version: 0.1a3.dev1
Summary: EIVideo - 交互式智能视频标注工具，几次鼠标点击即可解放双手，让视频标注更加轻松
Home-page: https://github.com/QPT-Family/EIVideo
Author: GT-ZhangAcer
Author-email: zhangacer@foxmail.com
License: LGPL
Platform: UNKNOWN
Requires-Python: >=3.7
Requires-Dist: numpy
Requires-Dist: pandas
Requires-Dist: tqdm
Requires-Dist: PyYAML (>=5.1)
Requires-Dist: opencv-python (==4.2.0.32)
Requires-Dist: decord (==0.4.2)
Requires-Dist: av (==8.0.3)
Requires-Dist: scipy (==1.6.3)
Requires-Dist: ffmpeg-python (==0.2.0)
Requires-Dist: scikit-image
Requires-Dist: matplotlib
Requires-Dist: paddlenlp
Requires-Dist: lmdb
Requires-Dist: SimpleITK
Requires-Dist: paddlevideo
Requires-Dist: davisinteractive
Requires-Dist: qeivideo
Requires-Dist: flask
Requires-Dist: flask-bootstrap
Requires-Dist: wget
